mcpywrap/__init__.py
mcpywrap/__main__.py
mcpywrap/cli.py
mcpywrap/config.py
mcpywrap/custom_packaging.py
mcpywrap/builders/AddonsPack.py
mcpywrap/builders/MapPack.py
mcpywrap/builders/__init__.py
mcpywrap/builders/dependency_manager.py
mcpywrap/builders/file_merge.py
mcpywrap/builders/project_builder.py
mcpywrap/builders/watcher.py
mcpywrap/commands/__init__.py
mcpywrap/commands/add_cmd.py
mcpywrap/commands/build_cmd.py
mcpywrap/commands/default_cmd.py
mcpywrap/commands/dev_cmd.py
mcpywrap/commands/edit_cmd.py
mcpywrap/commands/init_cmd.py
mcpywrap/commands/mod_cmd.py
mcpywrap/commands/modsdk_cmd.py
mcpywrap/commands/publish_cmd.py
mcpywrap/commands/remove_cmd.py
mcpywrap/commands/run_cmd.py
mcpywrap/commands/ui_cmd.py
mcpywrap/mcstudio/SimpleMonitor.py
mcpywrap/mcstudio/__init__.py
mcpywrap/mcstudio/editor.py
mcpywrap/mcstudio/game.py
mcpywrap/mcstudio/mcs.py
mcpywrap/mcstudio/runtime_cppconfig.py
mcpywrap/mcstudio/studio_server.py
mcpywrap/mcstudio/studio_server_ui.py
mcpywrap/mcstudio/symlink_helper_global.py
mcpywrap/mcstudio/symlink_helper_map.py
mcpywrap/mcstudio/symlinks.py
mcpywrap/minecraft/__init__.py
mcpywrap/minecraft/addons.py
mcpywrap/minecraft/level_dat.py
mcpywrap/minecraft/map.py
mcpywrap/minecraft/netease_modsdk.py
mcpywrap/minecraft/template/generate_mod_files.py
mcpywrap/minecraft/template/mod_template.py
mcpywrap/ui/__init__.py
mcpywrap/ui/project_ui.py
mcpywrap/utils/__init__.py
mcpywrap/utils/pip_error_parser.py
mcpywrap/utils/print_guide.py
mcpywrap/utils/project_setup.py
mcpywrap/utils/utils.py
mcpywrap-0.2.3.dist-info/licenses/LICENSE
mcpywrap-0.2.3.dist-info/METADATA
mcpywrap-0.2.3.dist-info/WHEEL
mcpywrap-0.2.3.dist-info/entry_points.txt
mcpywrap-0.2.3.dist-info/top_level.txt
mcpywrap-0.2.3.dist-info/RECORD
