Metadata-Version: 2.4
Name: mcpywrap
Version: 0.2.3
Summary: A wrapper for Minecraft China Edition Addons management
Author-email: boybook <boybook@easecation.net>
License: MIT
Project-URL: Homepage, https://github.com/EaseCation/mcpywrap
Project-URL: Bug Tracker, https://github.com/EaseCation/mcpywrap/issues
Classifier: Programming Language :: Python :: 3
Classifier: License :: OSI Approved :: MIT License
Classifier: Operating System :: OS Independent
Requires-Python: >=3.6
License-File: LICENSE
Requires-Dist: click>=8.0.0
Requires-Dist: watchdog>=2.0.0
Requires-Dist: twine>=3.4.0
Requires-Dist: tomli
Requires-Dist: tomli-w
Requires-Dist: setuptools
Requires-Dist: PyQt5>=5.15.0
Requires-Dist: psutil>=5.8.0
Requires-Dist: rich>=10.0.0
Dynamic: license-file
